<annotation>
	<folder>train</folder>
	<filename>63.png</filename>
	<path>/Users/isabelhinkle/Desktop/Pi-Ai/app/learningImages/clovers/train/63.png</path>
	<source>
		<database>Unknown</database>
	</source>
	<size>
		<width>512</width>
		<height>384</height>
		<depth>3</depth>
	</size>
	<segmented>0</segmented>
	<object>
		<name>clover</name>
		<pose>Unspecified</pose>
		<truncated>0</truncated>
		<difficult>0</difficult>
		<bndbox>
			<xmin>5</xmin>
			<ymin>5</ymin>
			<xmax>502</xmax>
			<ymax>377</ymax>
		</bndbox>
	</object>
</annotation>
