<annotation>
	<folder>images-2</folder>
	<filename>112.png</filename>
	<path>C:\Users\victo\Documents\capstone\practice1TF\models\research\object_detection\dandelions-and-clovers-relabeled\images-2\112.png</path>
	<source>
		<database>Unknown</database>
	</source>
	<size>
		<width>1668</width>
		<height>2224</height>
		<depth>3</depth>
	</size>
	<segmented>0</segmented>
	<object>
		<name>clover</name>
		<pose>Unspecified</pose>
		<truncated>0</truncated>
		<difficult>0</difficult>
		<bndbox>
			<xmin>631</xmin>
			<ymin>864</ymin>
			<xmax>1175</xmax>
			<ymax>1425</ymax>
		</bndbox>
	</object>
	<object>
		<name>clover</name>
		<pose>Unspecified</pose>
		<truncated>0</truncated>
		<difficult>0</difficult>
		<bndbox>
			<xmin>45</xmin>
			<ymin>1359</ymin>
			<xmax>573</xmax>
			<ymax>1827</ymax>
		</bndbox>
	</object>
	<object>
		<name>clover</name>
		<pose>Unspecified</pose>
		<truncated>1</truncated>
		<difficult>0</difficult>
		<bndbox>
			<xmin>3</xmin>
			<ymin>1808</ymin>
			<xmax>477</xmax>
			<ymax>2224</ymax>
		</bndbox>
	</object>
	<object>
		<name>clover</name>
		<pose>Unspecified</pose>
		<truncated>0</truncated>
		<difficult>0</difficult>
		<bndbox>
			<xmin>412</xmin>
			<ymin>1604</ymin>
			<xmax>917</xmax>
			<ymax>2101</ymax>
		</bndbox>
	</object>
	<object>
		<name>clover</name>
		<pose>Unspecified</pose>
		<truncated>0</truncated>
		<difficult>0</difficult>
		<bndbox>
			<xmin>1257</xmin>
			<ymin>1443</ymin>
			<xmax>1536</xmax>
			<ymax>1694</ymax>
		</bndbox>
	</object>
	<object>
		<name>clover</name>
		<pose>Unspecified</pose>
		<truncated>0</truncated>
		<difficult>0</difficult>
		<bndbox>
			<xmin>705</xmin>
			<ymin>318</ymin>
			<xmax>1173</xmax>
			<ymax>783</ymax>
		</bndbox>
	</object>
	<object>
		<name>clover</name>
		<pose>Unspecified</pose>
		<truncated>0</truncated>
		<difficult>0</difficult>
		<bndbox>
			<xmin>12</xmin>
			<ymin>192</ymin>
			<xmax>585</xmax>
			<ymax>841</ymax>
		</bndbox>
	</object>
	<object>
		<name>yellow wood sorrel</name>
		<pose>Unspecified</pose>
		<truncated>0</truncated>
		<difficult>0</difficult>
		<bndbox>
			<xmin>754</xmin>
			<ymin>1599</ymin>
			<xmax>1057</xmax>
			<ymax>1920</ymax>
		</bndbox>
	</object>
	<object>
		<name>yellow wood sorrel</name>
		<pose>Unspecified</pose>
		<truncated>0</truncated>
		<difficult>0</difficult>
		<bndbox>
			<xmin>764</xmin>
			<ymin>259</ymin>
			<xmax>938</xmax>
			<ymax>411</ymax>
		</bndbox>
	</object>
</annotation>
